setup.py
django_geoaware.egg-info/PKG-INFO
django_geoaware.egg-info/SOURCES.txt
django_geoaware.egg-info/dependency_links.txt
django_geoaware.egg-info/top_level.txt
geoaware/__init__.py
geoaware/context_processors.py
geoaware/defaults.py
geoaware/geo.py
geoaware/middleware.py
geoaware/models.py
geoaware/tests.py
geoaware/templatetags/__init__.py
geoaware/templatetags/geoaware.py