Metadata-Version: 1.1
Name: django-geoaware
Version: 0.5.0
Summary: A Django application that can include GeoIP info in session and/or context.
Home-page: https://github.com/un33k/django-geoaware
Author: Val Neekman
Author-email: info@neekware.com
License: BSD
Platform: UNKNOWN
Classifier: Development Status :: 4 - Beta
Classifier: Environment :: Web Environment
Classifier: Intended Audience :: Developers
Classifier: License :: OSI Approved :: BSD License
Classifier: Operating System :: OS Independent
Classifier: Programming Language :: Python
Classifier: Topic :: Utilities
